<annotation>
	<folder>all-images</folder>
	<filename>cats(35).jpeg</filename>
	<path>D:\DICT\Day 4\TF-Template\Tensorflow\workspace\images\all-images\cats(35).jpeg</path>
	<source>
		<database>Unknown</database>
	</source>
	<size>
		<width>299</width>
		<height>168</height>
		<depth>3</depth>
	</size>
	<segmented>0</segmented>
	<object>
		<name>cat</name>
		<pose>Unspecified</pose>
		<truncated>0</truncated>
		<difficult>0</difficult>
		<bndbox>
			<xmin>100</xmin>
			<ymin>24</ymin>
			<xmax>247</xmax>
			<ymax>163</ymax>
		</bndbox>
	</object>
</annotation>
